funalone/__init__.py
funalone/default_mocking_context.py
funalone/isolated_function_clone.py
funalone/namespaced_function.py
funalone/types.py
funalone-0.7.0.dist-info/LICENSE
funalone-0.7.0.dist-info/METADATA
funalone-0.7.0.dist-info/WHEEL
funalone-0.7.0.dist-info/RECORD
