Metadata-Version: 2.3
Name: funalone
Version: 0.7.0
Summary: Unittest functions isolated.
License: MIT
Author: Borja Martinena
Requires-Python: >=3.10,<4.0
Classifier: License :: OSI Approved :: MIT License
Classifier: Programming Language :: Python :: 3
Classifier: Programming Language :: Python :: 3.10
Classifier: Programming Language :: Python :: 3.11
Classifier: Programming Language :: Python :: 3.12
Classifier: Programming Language :: Python :: 3.13
Project-URL: Repository, https://github.com/aafrecct/funalone
